storr/__init__.py
storr/storr.py
storr-1.0.0.dist-info/LICENSE
storr-1.0.0.dist-info/METADATA
storr-1.0.0.dist-info/WHEEL
storr-1.0.0.dist-info/top_level.txt
storr-1.0.0.dist-info/RECORD
