Metadata-Version: 2.1
Name: storr
Version: 1.0.0
Summary: A painless way to store session data
Home-page: https://github.com/KrishaVyshak/storr
Author: Krishnavyshak R
Author-email: krishnavyshak.dev@gmail.com
License: UNKNOWN
Keywords: secure storage,session management,session data,encryption,data security,data privacy,data storage,data protection,data access,data retrieval,data encryption,data decryption,Fernet encryption,Python module,PyPI,session,storr,storing,store
Platform: UNKNOWN
License-File: LICENSE
Requires-Dist: cryptography
